csmp/__init__.py
csmp/compress.py
csmp/utils.py
csmp-0.1.0.dist-info/METADATA
csmp-0.1.0.dist-info/WHEEL
csmp-0.1.0.dist-info/top_level.txt
csmp-0.1.0.dist-info/RECORD
